lbson_py-0.1.0.dist-info/RECORD
lbson_py-0.1.0.dist-info/WHEEL
lbson_py-0.1.0.dist-info/METADATA
lbson_py-0.1.0.dist-info/licenses/LICENSE
lbson/_core.pyi
lbson/_version.py
lbson/__init__.py
lbson/_core.cpython-312-darwin.so
lbson/py.typed
