Metadata-Version: 2.2
Name: lbson-py
Version: 0.1.0
Summary: High-performance BSON library for Python without MongoDB dependencies
Keywords: bson,binary-json,serialization,encoding,decoding,mongodb,json,performance,cpp,pybind11
Author-Email: Soju06 <qlskssk@gmail.com>
Maintainer-Email: Soju06 <qlskssk@gmail.com>
Classifier: Development Status :: 4 - Beta
Classifier: Intended Audience :: Developers
Classifier: License :: OSI Approved :: MIT License
Classifier: Operating System :: OS Independent
Classifier: Programming Language :: Python :: 3
Classifier: Programming Language :: Python :: 3.9
Classifier: Programming Language :: Python :: 3.10
Classifier: Programming Language :: Python :: 3.11
Classifier: Programming Language :: Python :: 3.12
Classifier: Programming Language :: Python :: 3.13
Classifier: Programming Language :: C++
Classifier: Topic :: Software Development :: Libraries :: Python Modules
Classifier: Topic :: Database
Classifier: Topic :: Internet :: WWW/HTTP
Classifier: Topic :: System :: Archiving :: Compression
Classifier: Typing :: Typed
Project-URL: Homepage, https://github.com/Soju06/lbson
Project-URL: Documentation, https://github.com/Soju06/lbson#readme
Project-URL: Repository, https://github.com/Soju06/lbson.git
Project-URL: Bug Reports, https://github.com/Soju06/lbson/issues
Project-URL: Source Code, https://github.com/Soju06/lbson
Requires-Python: >=3.9
Provides-Extra: dev
Requires-Dist: pybind11-stubgen>=0.16; extra == "dev"
Requires-Dist: pytest>=8.4; extra == "dev"
Requires-Dist: orjson>=3.10; extra == "dev"
Requires-Dist: psutil>=7; extra == "dev"
Provides-Extra: test
Requires-Dist: pybind11-stubgen>=0.16; extra == "test"
Requires-Dist: pytest>=8.4; extra == "test"
Provides-Extra: benchmark
Requires-Dist: pybind11-stubgen>=0.16; extra == "benchmark"
Requires-Dist: orjson>=3.10; extra == "benchmark"
Requires-Dist: psutil>=7; extra == "benchmark"
